MANIFEST.in
README.md
pyproject.toml
setup.py
amuse_sse.egg-info/PKG-INFO
amuse_sse.egg-info/SOURCES.txt
amuse_sse.egg-info/dependency_links.txt
amuse_sse.egg-info/requires.txt
amuse_sse.egg-info/top_level.txt
src/amuse/community/sse/Makefile
src/amuse/community/sse/README
src/amuse/community/sse/__init__.py
src/amuse/community/sse/_version.py
src/amuse/community/sse/interface.f
src/amuse/community/sse/interface.py
src/amuse/community/sse/src/Makefile
src/amuse/community/sse/src/README_SSE
src/amuse/community/sse/src/const_bse.h
src/amuse/community/sse/src/deltat.f
src/amuse/community/sse/src/evolv1.f
src/amuse/community/sse/src/evolve.in
src/amuse/community/sse/src/hrdiag.f
src/amuse/community/sse/src/kick.f
src/amuse/community/sse/src/mlwind.f
src/amuse/community/sse/src/mrenv.f
src/amuse/community/sse/src/ran3.f
src/amuse/community/sse/src/sse.f
src/amuse/community/sse/src/star.f
src/amuse/community/sse/src/zcnsts.f
src/amuse/community/sse/src/zdata.h
src/amuse/community/sse/src/zfuncs.f
support/__init__.py
support/classifiers.py
support/config.py
support/generate_main.py
support/getsp.class
support/getsp.java
support/misc.py
support/setup_codes.py
support/version.py